{
  "info": {
    "name": "Telros API",
    "schema": "https://schema.getpostman.com/json/collection/v2.1.0/collection.json"
  },
  "item": [
    {
      "name": "Auth",
      "item": [
        {
          "name": "Register",
          "request": {
            "method": "POST",
            "header": [
              {
                "key": "Content-Type",
                "value": "application/json"
              }
            ],
            "body": {
              "mode": "raw",
              "raw": "{\n  \"username\": \"test_user\",\n  \"firstName\": \"Test123!\",\n  \"lastName\": \"Test123!\",\n  \"password\": \"Test123!\",\n  \"email\": \"test@example.com\"\n}"
            },
            "url": {
              "raw": "http://localhost:8080/api/auth/signup",
              "protocol": "http",
              "host": ["localhost"],
              "port": "8080",
              "path": ["api", "auth", "signup"]
            }
          }
        },
        {
          "name": "Login",
          "request": {
            "method": "POST",
            "header": [
              {
                "key": "Content-Type",
                "value": "application/json"
              }
            ],
            "body": {
              "mode": "raw",
              "raw": "{\n  \"username\": \"test_user\",\n  \"password\": \"Test123!\"\n}"
            },
            "url": {
              "raw": "http://localhost:8080/api/auth/signin",
              "protocol": "http",
              "host": ["localhost"],
              "port": "8080",
              "path": ["api", "auth", "signin"]
            }
          }
        }
      ]
    },
    {
      "name": "Users",
      "item": [
        {
          "name": "Get All Users (Admin)",
          "request": {
            "method": "GET",
            "header": [
              {
                "key": "Authorization",
                "value": "Bearer {{jwt_token}}"
              }
            ],
            "url": {
              "raw": "http://localhost:8080/api/users",
              "protocol": "http",
              "host": ["localhost"],
              "port": "8080",
              "path": ["api", "users"]
            }
          }
        },
        {
          "name": "Get Current User Details",
          "request": {
            "method": "GET",
            "header": [
              {
                "key": "Authorization",
                "value": "Bearer {{jwt_token}}"
              }
            ],
            "url": {
              "raw": "http://localhost:8080/api/users/me",
              "protocol": "http",
              "host": ["localhost"],
              "port": "8080",
              "path": ["api", "users", "me"]
            }
          }
        },
        {
          "name": "Upload Current User Photo",
          "request": {
            "method": "POST",
            "header": [
              {
                "key": "Authorization",
                "value": "Bearer {{jwt_token}}"
              }
            ],
            "body": {
              "mode": "formdata",
              "formdata": [
                {
                  "key": "file",
                  "type": "file",
                  "src": ""
                }
              ]
            },
            "url": {
              "raw": "http://localhost:8080/api/users/1/photo",
              "protocol": "http",
              "host": ["localhost"],
              "port": "8080",
              "path": ["api", "users", "1", "photo"]
            }
          }
        },
        {
          "name": "Get Current User Photo",
          "request": {
            "method": "GET",
            "header": [
              {
                "key": "Authorization",
                "value": "Bearer {{jwt_token}}"
              }
            ],
            "url": {
              "raw": "http://localhost:8080/api/users/1/photo",
              "protocol": "http",
              "host": ["localhost"],
              "port": "8080",
              "path": ["api", "users", "1", "photo"]
            }
          }
        },
        {
          "name": "Delete Current User Photo",
          "request": {
            "method": "DELETE",
            "header": [
              {
                "key": "Authorization",
                "value": "Bearer {{jwt_token}}"
              }
            ],
            "url": {
              "raw": "http://localhost:8080/api/users/1/photo",
              "protocol": "http",
              "host": ["localhost"],
              "port": "8080",
              "path": ["api", "users", "1", "photo"]
            }
          }
        },
        {
          "name": "Get User Details By ID (Admin)",
          "request": {
            "method": "GET",
            "header": [
              {
                "key": "Authorization",
                "value": "Bearer {{jwt_token}}"
              }
            ],
            "url": {
              "raw": "http://localhost:8080/api/users/1",
              "protocol": "http",
              "host": ["localhost"],
              "port": "8080",
              "path": ["api", "users", "1"]
            }
          }
        },
        {
          "name": "Update User Details By ID (Admin)",
          "request": {
            "method": "PUT",
            "header": [
              {
                "key": "Authorization",
                "value": "Bearer {{jwt_token}}"
              },
              {
                "key": "Content-Type",
                "value": "application/json"
              }
            ],
            "body": {
              "mode": "raw",
              "raw": "{\n  \"lastName\": \"Тестов\",\n  \"firstName\": \"Тест\",\n  \"middleName\": \"Тестович\",\n  \"birthDate\": \"1990-01-01\",\n  \"phoneNumber\": \"+7(999)999-99-99\"\n}"
            },
            "url": {
              "raw": "http://localhost:8080/api/users/1",
              "protocol": "http",
              "host": ["localhost"],
              "port": "8080",
              "path": ["api", "users", "1"]
            }
          }
        },
        {
          "name": "Delete User By ID (Admin)",
          "request": {
            "method": "DELETE",
            "header": [
              {
                "key": "Authorization",
                "value": "Bearer {{jwt_token}}"
              }
            ],
            "url": {
              "raw": "http://localhost:8080/api/users/1",
              "protocol": "http",
              "host": ["localhost"],
              "port": "8080",
              "path": ["api", "users", "1"]
            }
          }
        },
        {
          "name": "Upload User Photo By ID (Admin)",
          "request": {
            "method": "POST",
            "header": [
              {
                "key": "Authorization",
                "value": "Bearer {{jwt_token}}"
              }
            ],
            "body": {
              "mode": "formdata",
              "formdata": [
                {
                  "key": "file",
                  "type": "file",
                  "src": ""
                }
              ]
            },
            "url": {
              "raw": "http://localhost:8080/api/users/1/photo",
              "protocol": "http",
              "host": ["localhost"],
              "port": "8080",
              "path": ["api", "users", "1", "photo"]
            }
          }
        },
        {
          "name": "Get User Photo By ID",
          "request": {
            "method": "GET",
            "header": [
              {
                "key": "Authorization",
                "value": "Bearer {{jwt_token}}"
              }
            ],
            "url": {
              "raw": "http://localhost:8080/api/users/1/photo",
              "protocol": "http",
              "host": ["localhost"],
              "port": "8080",
              "path": ["api", "users", "1", "photo"]
            }
          }
        },
        {
          "name": "Delete User Photo By ID (Admin)",
          "request": {
            "method": "DELETE",
            "header": [
              {
                "key": "Authorization",
                "value": "Bearer {{jwt_token}}"
              }
            ],
            "url": {
              "raw": "http://localhost:8080/api/users/1/photo",
              "protocol": "http",
              "host": ["localhost"],
              "port": "8080",
              "path": ["api", "users", "1", "photo"]
            }
          }
        }
      ]
    }
  ],
  "variable": [
    {
      "key": "jwt_token",
      "value": ""
    }
  ]
}